minswap_oura/__init__.py
minswap_oura/adapter.py
minswap_oura/constants.py
minswap_oura/oura_adapter.py
minswap_oura/pool.py
minswap_oura/types.py
minswap_oura-0.1.4.dist-info/WHEEL
minswap_oura-0.1.4.dist-info/METADATA
minswap_oura-0.1.4.dist-info/RECORD
