Metadata-Version: 2.1
Name: minswap-oura
Version: 0.1.4
Summary: 
Home-page: https://github.com/sostholm/minswap
Author: Samuel Ostholm
Author-email: kalltrum@gmail.com
Requires-Python: >=3.8,<4.0
Classifier: Programming Language :: Python :: 3
Classifier: Programming Language :: Python :: 3.10
Classifier: Programming Language :: Python :: 3.8
Classifier: Programming Language :: Python :: 3.9
Requires-Dist: blockfrost-python (==0.4.4)
Project-URL: Repository, https://github.com/sostholm/minswap
